crif
