Metadata-Version: 1.0
Name: create-ios-framework
Version: 0.1.5
Summary: a tool to create iOS framework
Home-page: http://github.com/epingwang/createiosframework
Author: Wang YiPing
Author-email: me@epingwang.me
License: MIT
Platform: UNKNOWN
